flask_rethinkview/__init__.py
flask_rethinkview/response.py
flask_rethinkview/rethinkdb_util.py
flask_rethinkview/validator.py
flask_rethinkview/views.py
flask_rethinkview-0.1.2.dist-info/DESCRIPTION.rst
flask_rethinkview-0.1.2.dist-info/METADATA
flask_rethinkview-0.1.2.dist-info/RECORD
flask_rethinkview-0.1.2.dist-info/WHEEL
flask_rethinkview-0.1.2.dist-info/metadata.json
flask_rethinkview-0.1.2.dist-info/top_level.txt
