Metadata-Version: 2.0
Name: flask-rethinkview
Version: 0.1.2
Summary: RESTful Flask View with RethinkDB
Home-page: https://github.com/lucidfrontier45/flask-rethinkview
Author: Shiqiao Du
Author-email: lucidfrontier.45@gmail.com
License: MIT
Platform: UNKNOWN
Requires-Dist: flask
Requires-Dist: flask-classful
Requires-Dist: jsonschema
Requires-Dist: pyfunctional (==0.6)
Requires-Dist: rethinkdb
